chunkdup/__init__.py
chunkdup/blueprint.py
chunkdup/chunkdiff.py
chunkdup/chunkdup.py
chunkdup/diffbar.py
chunkdup/differ.py
chunkdup/dire.py
chunkdup/sums.py
chunkdup/utils.py
chunkdup-0.5.0.dist-info/entry_points.txt
chunkdup-0.5.0.dist-info/LICENSE
chunkdup-0.5.0.dist-info/WHEEL
chunkdup-0.5.0.dist-info/METADATA
chunkdup-0.5.0.dist-info/RECORD
