Metadata-Version: 2.1
Name: chunkdup
Version: 0.5.0
Summary: Find (partial content) duplicate files.
Home-page: https://github.com/xyb/chunkdup
License: MIT
Author: Xie Yanbo
Author-email: xieyanbo@gmail.com
Requires-Python: >=3.7,<4.0
Classifier: Development Status :: 4 - Beta
Classifier: Environment :: Console
Classifier: License :: OSI Approved :: MIT License
Classifier: Programming Language :: Python :: 3
Classifier: Programming Language :: Python :: 3.7
Classifier: Programming Language :: Python :: 3.8
Classifier: Programming Language :: Python :: 3.9
Classifier: Programming Language :: Python :: 3.10
Classifier: Programming Language :: Python :: 3.11
Classifier: Topic :: Desktop Environment :: File Managers
Classifier: Topic :: Terminals
Classifier: Topic :: Utilities
Requires-Dist: chunksum
Project-URL: Bug Tracker, https://github.com/xyb/chunkdup/issues
Project-URL: Repository, https://github.com/xyb/chunkdup
